MANIFEST.in
README.md
setup.py
../hello.txt
hello_from_file/__init__.py
hello_from_file/main.py
hello_from_file.egg-info/PKG-INFO
hello_from_file.egg-info/SOURCES.txt
hello_from_file.egg-info/dependency_links.txt
hello_from_file.egg-info/top_level.txt