Metadata-Version: 2.1
Name: hello-from-file
Version: 1.0.0
Summary: Just a random package
License: MIT
